repgen/__init__.py
repgen/repgen.py
repgen-0.0.2.dist-info/LICENSE
repgen-0.0.2.dist-info/METADATA
repgen-0.0.2.dist-info/WHEEL
repgen-0.0.2.dist-info/top_level.txt
repgen-0.0.2.dist-info/RECORD
