Metadata-Version: 2.1
Name: repgen
Version: 0.0.2
Summary: A simple python REPort GENeration library
Home-page: https://github.com/liborw/repgen
Author: Libor Wagner
Author-email: libor.wagner@cvut.cz
License: UNKNOWN
Platform: UNKNOWN
Classifier: Programming Language :: Python :: 3
Classifier: Programming Language :: Python :: 2
Classifier: License :: OSI Approved :: MIT License
Requires-Dist: jinja2
